xlsx_xargs.py
xlsx_xargs-0.1.0.dist-info/LICENSE
xlsx_xargs-0.1.0.dist-info/METADATA
xlsx_xargs-0.1.0.dist-info/WHEEL
xlsx_xargs-0.1.0.dist-info/entry_points.txt
xlsx_xargs-0.1.0.dist-info/top_level.txt
xlsx_xargs-0.1.0.dist-info/RECORD
