Metadata-Version: 2.1
Name: xlsx-xargs
Version: 0.1.0
Summary: 类似xargs命令，遍历依据是excel表单中的每一行。命令参数，允许被string.format替换，替换内容为指定单元格值。
Home-page: https://github.com/appstore-zencore/xlsx-xargs
Author: zencore
Author-email: dobetter@zencore.cn
License: MIT
Keywords: openpyxl,xlsx split,excel split
Platform: UNKNOWN
Classifier: Development Status :: 5 - Production/Stable
Classifier: Intended Audience :: Developers
Classifier: Topic :: Software Development :: Libraries :: Python Modules
Classifier: License :: OSI Approved :: MIT License
Classifier: Programming Language :: Python :: 3
Classifier: Programming Language :: Python :: 3 :: Only
Requires: click
Requires: openpyxl
Requires: xlsxhelper
Requires-Dist: click
Requires-Dist: openpyxl
Requires-Dist: xlsxhelper
